FlyForms-0.3.0.dist-info/DESCRIPTION.rst
FlyForms-0.3.0.dist-info/METADATA
FlyForms-0.3.0.dist-info/RECORD
FlyForms-0.3.0.dist-info/WHEEL
FlyForms-0.3.0.dist-info/metadata.json
FlyForms-0.3.0.dist-info/top_level.txt
flyforms/__init__.py
flyforms/common.py
flyforms/compatibility.py
flyforms/fields.py
flyforms/form.py
flyforms/validators.py
