Metadata-Version: 2.0
Name: FlyForms
Version: 0.3.0
Summary: FlyForms is flexible and easy to use Python library for data structures defining and validation.
Home-page: https://bitbucket.org/ShabashP/flyforms
Author: Pavel Sizov
Author-email: shabash1991@yandex.ru
License: MIT
Keywords: validation,structures,form,forms,validator,schema,data
Platform: UNKNOWN
Classifier: Development Status :: 5 - Production/Stable
Classifier: Intended Audience :: Developers
Classifier: Operating System :: OS Independent
Classifier: Programming Language :: Python
Classifier: Programming Language :: Python :: 2.7
Classifier: Programming Language :: Python :: 3.5
